bp/__init__.py
bp/experiment.py
bp/serve_model.py
bp/split_data.py
bp/train_pipeline.py
processing/__init__.py
processing/config.py
processing/data_management.py
processing/errors.py
processing/model_builder.py
processing/pipeline.py
processing/preprocessors.py
processing/utils.py
processing/validation.py
kueski_exam_cesar0205-0.0.4.dist-info/LICENSE
kueski_exam_cesar0205-0.0.4.dist-info/METADATA
kueski_exam_cesar0205-0.0.4.dist-info/WHEEL
kueski_exam_cesar0205-0.0.4.dist-info/top_level.txt
kueski_exam_cesar0205-0.0.4.dist-info/RECORD
