Metadata-Version: 2.1
Name: kueski-exam-cesar0205
Version: 0.0.4
Summary: Processing tools
Home-page: https://github.com/pypa/sampleproject
Author: César Juárez Ramírez
Author-email: cesaripn2@gmail.com
License: UNKNOWN
Platform: UNKNOWN
Classifier: Programming Language :: Python :: 3
Classifier: License :: OSI Approved :: MIT License
Classifier: Operating System :: OS Independent
Requires-Python: >=3.6
